isp_git_hooks/__init__.py
isp_git_hooks/pre_commit_hooks/check_deze.py
isp_git_hooks-0.9.1.dist-info/entry_points.txt
isp_git_hooks-0.9.1.dist-info/WHEEL
isp_git_hooks-0.9.1.dist-info/METADATA
isp_git_hooks-0.9.1.dist-info/RECORD
